{
    "condition_key_word_list": [
        {
            "key": "counter",
            "value": "计数器"
        },
        {
            "key": "error_number",
            "value": "ERRNO"
        },
        {
            "key": "timer",
            "value": "计时器"
        }
    ],
    "key_word_list": [
        {
            "key": "start",
            "value": "启动"
        },
        {
            "key": "stop",
            "value": "停止"
        },
        {
            "key": "move_line",
            "value": "ML"
        },
        {
            "key": "move_joint",
            "value": "MJ"
        },
        {
            "key": "catch",
            "value": "抓"
        },
        {
            "key": "release",
            "value": "放"
        },
        {
            "key": "error_number",
            "value": "ERRNO"
        },
        {
            "key": "timer",
            "value": "计时器"
        },
        {
            "key": "counter",
            "value": "计数器"
        },
        {
            "key": "while",
            "value": "while"
        },
        {
            "key": "if",
            "value": "if"
        },
        {
            "key": "pause",
            "value": "暂停"
        },
        {
            "key": "sleep",
            "value": "休眠"
        },
        {
            "key": "task_static_catch",
            "value": "静态抓取算子"
        },
        {
            "key": "task_dynamic_catch",
            "value": "动态抓取算子"
        }
    ],
    "task_id": [
        {
            "key_word": "start"
        },
        {
            "key_word": "move_joint",
            "argument_id": "11474915599209436650",
            "argument_speedpercent": 10,
            "argument_robot_tool_index": 1,
            "argument_robot_tool_name": "one",
            "argument_robot_tool_mass": 2,
            "argument_robot_tool_position": [
                0,
                0,
                0,
                0,
                0,
                0
            ],
            "argument_robot_tool_center_of_mass": [
                0,
                0,
                0
            ],
            "argument_robot_tool_inertia": [
                0,
                0,
                0,
                0,
                0,
                0,
                0,
                0,
                0
            ],
            "argument_target": [
                0,
                0,
                1.57,
                0,
                1.57,
                0
            ]
        },
        {
            "key_word": "move_line",
            "argument_id": "11474915599209436650",
            "argument_cart_vel": 0.02,
            "argument_rot_vel": 0.2,
            "argument_robot_tool_index": 1,
            "argument_robot_tool_name": "one",
            "argument_robot_tool_mass": 2,
            "argument_robot_tool_position": [
                0,
                0,
                0,
                0,
                0,
                0
            ],
            "argument_robot_tool_center_of_mass": [
                0,
                0,
                0
            ],
            "argument_robot_tool_inertia": [
                0,
                0,
                0,
                0,
                0,
                0,
                0,
                0,
                0
            ],
            "argument_target": [
                -0.101099,
                -0.297817,
                0.0557633,
                -2.20871,
                2.1390289,
                0.1048353
            ]
        },
        {
            "key_word": "while",
            "condition_key_word": "counter",
            "condition_value": "10",
            "condition_operator": ">",
            "process": [
                {
                    "key_word": "counter",
                    "argument_operator": "+",
                    "argument_value": 1
                },
                {
                    "key_word": "move_joint",
                    "argument_id": "11474915599209436650",
                    "argument_speedpercent": 10,
                    "argument_target": [
                        0,
                        0,
                        1.57,
                        0,
                        1.57,
                        0
                    ]
                },
                {
                    "key_word": "move_line",
                    "argument_id": "11474915599209436650",
                    "argument_cart_vel": 0.02,
                    "argument_rot_vel": 0.2,
                    "argument_target": [
                        -0.101099,
                        -0.297817,
                        0.0557633,
                        -2.20871,
                        2.1390289,
                        0.1048353
                    ]
                },
                {
                    "key_word": "pause"
                },
                {
                    "key_word": "move_line",
                    "argument_id": "11474915599209436650",
                    "argument_cart_vel": 0.02,
                    "argument_rot_vel": 0.2,
                    "argument_target": [
                        -0.051099,
                        -0.297817,
                        0.0557633,
                        -2.20871,
                        2.1390289,
                        0.1048353
                    ]
                },
                {
                    "key_word": "move_joint",
                    "argument_id": "11474915599209436650",
                    "argument_speedpercent": 10,
                    "argument_target": [
                        0,
                        0,
                        1.57,
                        0,
                        1.57,
                        0
                    ]
                }
            ]
        },
        {
            "key_word": "catch",
            "argument_id": "9731621822652897745"
        },
        {
            "key_word": "sleep",
            "argument_sleep": 3
        },
        {
            "key_word": "release",
            "argument_id": "9731621822652897745"
        },
        {
            "key_word": "if",
            "condition_key_word": "counter",
            "condition_value": "100",
            "condition_operator": ">",
            "true_process": [
                {
                    "key_word": "catch",
                    "argument_id": "9731621822652897745"
                },
                {
                    "key_word": "move_joint",
                    "argument_id": "11474915599209436650",
                    "argument_speedpercent": 10,
                    "argument_target": [
                        0,
                        0,
                        1.57,
                        0,
                        1.57,
                        0
                    ]
                }
            ],
            "false_process": [
                {
                    "key_word": "release",
                    "argument_id": "9731621822652897745"
                },
                {
                    "key_word": "move_line",
                    "argument_id": "11474915599209436650",
                    "argument_cart_vel": 0.02,
                    "argument_rot_vel": 0.2,
                    "argument_target": [
                        -0.101099,
                        -0.297817,
                        0.0957633,
                        -2.20871,
                        2.1390289,
                        0.1048353
                    ]
                }
            ]
        },
        {
            "key_word": "release",
            "argument_id": "9731621822652897745"
        },
        {
            "key_word": "stop"
        }
    ]
}